wafermap/__init__.py
wafermap/utils.py
wafermap/wafermap.py
wafermap-0.3.2.dist-info/licenses/LICENSE
wafermap-0.3.2.dist-info/METADATA
wafermap-0.3.2.dist-info/WHEEL
wafermap-0.3.2.dist-info/RECORD
