Metadata-Version: 2.4
Name: wafermap
Version: 0.3.2
Summary: A python package to plot maps of semiconductor wafers.
License: MIT
License-File: LICENSE
Keywords: semiconductor,wafer,layout,plot,grid
Author: Sotiris Thomas
Author-email: sothomas88@gmail.com
Requires-Python: >=3.10,<4.0
Classifier: License :: OSI Approved :: MIT License
Classifier: Programming Language :: Python :: 3
Classifier: Programming Language :: Python :: 3.10
Classifier: Programming Language :: Python :: 3.11
Classifier: Programming Language :: Python :: 3.12
Classifier: Programming Language :: Python :: 3.13
Classifier: Programming Language :: Python :: 3.14
Provides-Extra: test
Requires-Dist: Pillow (>=12.0.0)
Requires-Dist: black ; extra == "test"
Requires-Dist: branca (>=0.6.0)
Requires-Dist: flake8 ; extra == "test"
Requires-Dist: flake8-docstrings ; extra == "test"
Requires-Dist: folium (>=0.19.5)
Requires-Dist: html2image (>=2.0.3)
Requires-Dist: isort ; extra == "test"
Requires-Dist: numpy (>=2.00.0)
Requires-Dist: pylint ; extra == "test"
Requires-Dist: pytest ; extra == "test"
Requires-Dist: pytest-cov ; extra == "test"
Requires-Dist: tox ; extra == "test"
Requires-Dist: tox-poetry-installer ; extra == "test"
Requires-Dist: twine ; extra == "test"
